repurpose/__init__.py
repurpose/img2ts.py
repurpose/misc.py
repurpose/process.py
repurpose/resample.py
repurpose/stack.py
repurpose/ts2img.py
repurpose-0.13.2.dist-info/AUTHORS.rst
repurpose-0.13.2.dist-info/LICENSE.txt
repurpose-0.13.2.dist-info/METADATA
repurpose-0.13.2.dist-info/WHEEL
repurpose-0.13.2.dist-info/top_level.txt
repurpose-0.13.2.dist-info/RECORD
