Metadata-Version: 2.2
Name: repurpose
Version: 0.13.2
Summary: Package for image to timeseries to image conversion
Home-page: https://repurpose.readthedocs.io/en/latest/
Author: TU Wien
Author-email: remote.sensing@geo.tuwien.ac.at
License: mit
Project-URL: Documentation, https://repurpose.readthedocs.io/en/latest/
Platform: any
Classifier: Development Status :: 4 - Beta
Classifier: Programming Language :: Python
Requires-Python: >=3.8
License-File: LICENSE.txt
License-File: AUTHORS.rst
Requires-Dist: importlib-metadata; python_version < "3.8"
Requires-Dist: numpy
Requires-Dist: pygeogrids>=0.1.3
Requires-Dist: netCDF4
Requires-Dist: pynetcf>=0.5.1
Requires-Dist: xarray
Requires-Dist: pyresample
Requires-Dist: tqdm
Requires-Dist: more_itertools
Requires-Dist: joblib
Requires-Dist: yapf
Provides-Extra: testing
Requires-Dist: smecv_grid; extra == "testing"
Requires-Dist: pytest; extra == "testing"
Requires-Dist: pytest-cov; extra == "testing"
Requires-Dist: cadati; extra == "testing"
Provides-Extra: docs
Requires-Dist: ipykernel; extra == "docs"
Requires-Dist: nbconvert; extra == "docs"
Requires-Dist: matplotlib; extra == "docs"
Requires-Dist: nbsphinx; extra == "docs"
Requires-Dist: sphinx_rtd_theme; extra == "docs"
